dot_i18n-0.2.1.dist-info/licenses/LICENSE
doti18n/__init__.py
doti18n/locale_data.py
doti18n/locale_translator.py
doti18n/utils.py
doti18n/wrapped/__init__.py
doti18n/wrapped/locale_list.py
doti18n/wrapped/locale_namespace.py
doti18n/wrapped/none_wrapper.py
doti18n/wrapped/plural_wrapper.py
dot_i18n-0.2.1.dist-info/METADATA
dot_i18n-0.2.1.dist-info/WHEEL
dot_i18n-0.2.1.dist-info/top_level.txt
dot_i18n-0.2.1.dist-info/RECORD
