Metadata-Version: 2.4
Name: dot-i18n
Version: 0.2.1
Summary: Python library for loading YAML localizations with dot access and pluralization.
Author-email: darkj3suss <asdzxco@protonmail.com>
License-Expression: MIT
Project-URL: Homepage, https://github.com/darkj3suss/dot-i18n
Project-URL: BugTracker, https://github.com/darkj3suss/dot-i18n/issues
Project-URL: Repository, https://github.com/darkj3suss/dot-i18n
Keywords: localization,i18n,l10n,translate,yaml,dot access,pluralization,babel
Classifier: Programming Language :: Python :: 3
Classifier: Programming Language :: Python :: 3.8
Classifier: Programming Language :: Python :: 3.9
Classifier: Programming Language :: Python :: 3.10
Classifier: Programming Language :: Python :: 3.11
Classifier: Programming Language :: Python :: 3.12
Classifier: Operating System :: OS Independent
Classifier: Development Status :: 3 - Alpha
Classifier: Intended Audience :: Developers
Classifier: Topic :: Software Development :: Libraries :: Python Modules
Classifier: Topic :: Software Development :: Localization
Classifier: Topic :: Text Processing :: Linguistic
Requires-Python: >=3.8
License-File: LICENSE
Requires-Dist: PyYAML>=6.0
Provides-Extra: pluralization
Requires-Dist: babel>=2.17; extra == "pluralization"
Dynamic: license-file
